CHANGES.md
INSTALL.md
MANIFEST.in
README.md
pyproject.toml
setup.py
krypton_cryptofeed/__init__.py
krypton_cryptofeed/callback.py
krypton_cryptofeed/config.py
krypton_cryptofeed/connection.py
krypton_cryptofeed/connection_handler.py
krypton_cryptofeed/defines.py
krypton_cryptofeed/exceptions.py
krypton_cryptofeed/exchange.py
krypton_cryptofeed/feed.py
krypton_cryptofeed/feedhandler.py
krypton_cryptofeed/log.py
krypton_cryptofeed/nbbo.py
krypton_cryptofeed/raw_data_collection.py
krypton_cryptofeed/symbols.py
krypton_cryptofeed/types.c
krypton_cryptofeed/types.pyx
krypton_cryptofeed.egg-info/PKG-INFO
krypton_cryptofeed.egg-info/SOURCES.txt
krypton_cryptofeed.egg-info/dependency_links.txt
krypton_cryptofeed.egg-info/requires.txt
krypton_cryptofeed.egg-info/top_level.txt
krypton_cryptofeed/backends/__init__.py
krypton_cryptofeed/backends/_util.py
krypton_cryptofeed/backends/aggregate.py
krypton_cryptofeed/backends/arctic.py
krypton_cryptofeed/backends/backend.py
krypton_cryptofeed/backends/gcppubsub.py
krypton_cryptofeed/backends/http.py
krypton_cryptofeed/backends/influxdb.py
krypton_cryptofeed/backends/kafka.py
krypton_cryptofeed/backends/mongo.py
krypton_cryptofeed/backends/postgres.py
krypton_cryptofeed/backends/quest.py
krypton_cryptofeed/backends/rabbitmq.py
krypton_cryptofeed/backends/redis.py
krypton_cryptofeed/backends/socket.py
krypton_cryptofeed/backends/zmq.py
krypton_cryptofeed/exchanges/__init__.py
krypton_cryptofeed/exchanges/ascendex.py
krypton_cryptofeed/exchanges/ascendex_futures.py
krypton_cryptofeed/exchanges/bequant.py
krypton_cryptofeed/exchanges/binance.py
krypton_cryptofeed/exchanges/binance_delivery.py
krypton_cryptofeed/exchanges/binance_futures.py
krypton_cryptofeed/exchanges/binance_us.py
krypton_cryptofeed/exchanges/bitdotcom.py
krypton_cryptofeed/exchanges/bitfinex.py
krypton_cryptofeed/exchanges/bitflyer.py
krypton_cryptofeed/exchanges/bitget.py
krypton_cryptofeed/exchanges/bithumb.py
krypton_cryptofeed/exchanges/bitmex.py
krypton_cryptofeed/exchanges/bitstamp.py
krypton_cryptofeed/exchanges/bittrex.py
krypton_cryptofeed/exchanges/blockchain.py
krypton_cryptofeed/exchanges/bybit.py
krypton_cryptofeed/exchanges/coinbase.py
